havenlighting/__init__.py
havenlighting/client.py
havenlighting/config.py
havenlighting/credentials.py
havenlighting/exceptions.py
havenlighting/logging.py
havenlighting/models.py
havenlighting/devices/light.py
havenlighting/devices/location.py
havenlighting-0.1.5.dist-info/METADATA
havenlighting-0.1.5.dist-info/WHEEL
havenlighting-0.1.5.dist-info/top_level.txt
havenlighting-0.1.5.dist-info/RECORD
