Metadata-Version: 2.1
Name: havenlighting
Version: 0.1.5
Summary: Python client for Haven Lighting API
Author-email: Mickey Schwab <mickeyschwab@gmail.com>
Requires-Python: >=3.7
Requires-Dist: requests>=2.25.0
Provides-Extra: dev
Requires-Dist: pytest>=6.0; extra == "dev"
Requires-Dist: pytest-mock>=3.0; extra == "dev"
